<?xml version="1.0" encoding="ISO-8859-6" ?>
<!DOCTYPE ViewObject SYSTEM "jbo_03_01.dtd">
<!---->
<ViewObject
  xmlns="http://xmlns.oracle.com/bc4j"
  Name="LocationMstVO"
  Version="11.1.1.64.93"
  InheritPersonalization="true"
  OrderBy="Created_Date desc"
  BindingStyle="JDBC"
  CustomQuery="true"
  PageIterMode="Full"
  UseGlueCode="false"
  RowClass="com.imum.cpms.model.masters.vo.LocationMstVORowImpl"
  ComponentClass="com.imum.cpms.model.masters.vo.LocationMstVOImpl">
  <DesignTime>
    <Attr Name="_isExpertMode" Value="true"/>
    <Attr Name="_codeGenFlag2" Value="Access|Coll|Prog|VarAccess"/>
    <Attr Name="_isCodegen" Value="true"/>
  </DesignTime>
  <Properties>
    <SchemaBasedProperties>
      <LABEL
        ResId="com.imum.cpms.model.masters.vo.LocationMstVO_LABEL"/>
    </SchemaBasedProperties>
  </Properties>
  <ViewAccessor
    Name="YesNoLovVO1"
    ViewObjectName="com.imum.cpms.model.masters.vo.YesNoLovVO"
    RowLevelBinds="true"/>
  <ViewAccessor
    Name="CommunityLovVO1"
    ViewObjectName="com.imum.cpms.model.masters.vo.CommunityLovVO">
    <ViewCriteriaUsage
      Name="CommunityLovVOCriteria"
      FullName="com.imum.cpms.model.masters.vo.CommunityLovVO.CommunityLovVOCriteria"/>
    <ParameterMap>
      <PIMap Variable="lng">
        <TransientExpression><![CDATA[adf.context.locale.language]]></TransientExpression>
      </PIMap>
    </ParameterMap>
  </ViewAccessor>
  <ViewAccessor
    Name="CountryLovVO1"
    ViewObjectName="com.imum.cpms.model.masters.vo.CountryLovVO">
    <ViewCriteriaUsage
      Name="CountryLovVOCriteria"
      FullName="com.imum.cpms.model.masters.vo.CountryLovVO.CountryLovVOCriteria"/>
    <ParameterMap>
      <PIMap Variable="lng">
        <TransientExpression><![CDATA[adf.context.locale.language]]></TransientExpression>
      </PIMap>
    </ParameterMap>
  </ViewAccessor>
  <ViewAccessor
    Name="CityLovVO1"
    ViewObjectName="com.imum.cpms.model.masters.vo.CityLovVO">
    <ViewCriteriaUsage
      Name="CityLovVOCriteria"
      FullName="com.imum.cpms.model.masters.vo.CityLovVO.CityLovVOCriteria"/>
    <ParameterMap>
      <PIMap Variable="lng">
        <TransientExpression><![CDATA[adf.context.locale.language]]></TransientExpression>
      </PIMap>
    </ParameterMap>
  </ViewAccessor>
  <ViewAccessor
    Name="LocationTypeLVO1"
    ViewObjectName="com.imum.cpms.model.masters.vo.LocationTypeLVO"
    RowLevelBinds="true"/>
  <ViewAccessor
    Name="CityLovVO4"
    ViewObjectName="com.imum.cpms.model.masters.vo.CityLovVO">
    <ViewCriteriaUsage
      Name="CityLovVOCriteria"
      FullName="com.imum.cpms.model.masters.vo.CityLovVO.CityLovVOCriteria"/>
    <ParameterMap>
      <PIMap Variable="lng">
        <TransientExpression><![CDATA[adf.context.locale.language]]></TransientExpression>
      </PIMap>
    </ParameterMap>
  </ViewAccessor>
  <ViewAccessor
    Name="LangMstLVO1"
    ViewObjectName="com.imum.cpms.model.masters.vo.LangMstLVO">
    <ViewCriteriaUsage
      Name="LangMstLVOCriteria"
      FullName="com.imum.cpms.model.masters.vo.LangMstLVO.LangMstLVOCriteria"/>
    <ParameterMap>
      <PIMap Variable="lng">
        <TransientExpression><![CDATA[adf.context.locale.language]]></TransientExpression>
      </PIMap>
    </ParameterMap>
  </ViewAccessor>
  <ListBinding
    Name="LOV_ActiveFlag"
    ListVOName="YesNoLovVO1"
    ListRangeSize="-1"
    NullValueFlag="none"
    NullValueId="LOV_ActiveFlag_LOVUIHints_NullValueId"
    MRUCount="0">
    <AttrArray Name="AttrNames">
      <Item Value="ActiveFlag"/>
    </AttrArray>
    <AttrArray Name="ListAttrNames">
      <Item Value="Code"/>
    </AttrArray>
    <AttrArray Name="ListDisplayAttrNames">
      <Item Value="Meaning"/>
    </AttrArray>
    <DisplayCriteria/>
  </ListBinding>
  <ListBinding
    Name="LOV_COUNTRYCODE"
    ListVOName="CountryLovVO1"
    ListRangeSize="-1"
    NullValueFlag="none"
    NullValueId="LOV_COUNTRYCODE_LOVUIHints_NullValueId"
    MRUCount="0">
    <AttrArray Name="AttrNames">
      <Item Value="COUNTRYCODE"/>
    </AttrArray>
    <AttrArray Name="ListAttrNames">
      <Item Value="CountryCode"/>
    </AttrArray>
    <AttrArray Name="ListDisplayAttrNames">
      <Item Value="CountryName"/>
    </AttrArray>
    <DisplayCriteria/>
  </ListBinding>
  <ListBinding
    Name="LOV_CommunityCode"
    ListVOName="CommunityLovVO1"
    ListRangeSize="-1"
    NullValueFlag="none"
    NullValueId="LOV_CommunityCode_LOVUIHints_NullValueId"
    MRUCount="0">
    <AttrArray Name="AttrNames">
      <Item Value="CommunityCode"/>
    </AttrArray>
    <AttrArray Name="ListAttrNames">
      <Item Value="CommunityCode"/>
    </AttrArray>
    <AttrArray Name="ListDisplayAttrNames">
      <Item Value="CommunityName"/>
    </AttrArray>
    <DisplayCriteria/>
  </ListBinding>
  <ListBinding
    Name="LOV_LOCTYPE"
    ListVOName="LocationTypeLVO1"
    ListRangeSize="-1"
    NullValueFlag="none"
    NullValueId="LOV_LOCTYPE_LOVUIHints_NullValueId"
    MRUCount="0">
    <AttrArray Name="AttrNames">
      <Item Value="LOCTYPE"/>
    </AttrArray>
    <AttrArray Name="ListAttrNames">
      <Item Value="ValueCode"/>
    </AttrArray>
    <AttrArray Name="ListDisplayAttrNames">
      <Item Value="ValueDesc"/>
    </AttrArray>
    <DisplayCriteria/>
  </ListBinding>
  <ListBinding
    Name="LOV_Language"
    ListVOName="LangMstLVO1"
    ListRangeSize="-1"
    NullValueFlag="none"
    NullValueId="LOV_Language_LOVUIHints_NullValueId"
    MRUCount="0">
    <AttrArray Name="AttrNames">
      <Item Value="Language"/>
    </AttrArray>
    <AttrArray Name="ListAttrNames">
      <Item Value="LNGCODE"/>
    </AttrArray>
    <AttrArray Name="ListDisplayAttrNames">
      <Item Value="LNGDESC"/>
    </AttrArray>
    <DisplayCriteria/>
  </ListBinding>
  <SQLQuery>
    <![CDATA[SELECT LocationMstEO.Active_Flag, 
       LocationMstEO.Addl_Charge, 
       LocationMstEO.Bay_Count, 
       LocationMstEO.COUNTRY_CODE, 
       LocationMstEO.Clamping_charges, 
       LocationMstEO.Community_Code, 
       LocationMstEO.Contact_Details, 
       LocationMstEO.Created_By, 
       LocationMstEO.Created_Date, 
       LocationMstEO.Free_days, 
       LocationMstEO.Geo_lat_deg, 
       LocationMstEO.Geo_lon_deg, 
       LocationMstEO.GoLive_Dt, 
       LocationMstEO.LOC_TYPE, 
       LocationMstEO.Loc_Add1, 
       LocationMstEO.Loc_Add2, 
       LocationMstEO.Loc_Desc, 
       LocationMstEO.Location_ID, 
       LocationMstEO.Opening_Dt, 
       LocationMstEO.Opr_Hr_From, 
       LocationMstEO.Opr_Hr_To, 
       LocationMstEO.PO_Box, 
       LocationMstEO.Removal_Charge, 
       LocationMstEO.Updated_By, 
       LocationMstEO.Updated_Date, 
       LocationMstEO.iss_Comm_Prmit_flag, 
       LocationMstEO.iss_Govt_Permit_flag,
       LocationMstEO.Remarks,
 LocationMstEO.Allow_Commercial_Permits_flag, 
       LocationMstEO.Storage_charge,
(select UPPER(country_name) from  gen_country_mst where country_code = LocationMstEO.COUNTRY_CODE)Country_Name,
(select UPPER(Community_Name) from  GEN_COMMUNITY_MST where Community_Code = LocationMstEO.Community_Code)Community_Name,
(select UPPER(Value_Desc) from  gen_ref_data_detail_mst where Value_Code = LocationMstEO.LOC_TYPE and ref_data_header_seq=11)LocationType_Name
   
FROM GEN_LOCATION_MST LocationMstEO]]>
  </SQLQuery>
  <EntityUsage
    Name="LocationMstEO"
    Entity="com.imum.cpms.model.masters.eo.LocationMstEO"/>
  <ViewAttribute
    Name="ActiveFlag"
    LOVName="LOV_ActiveFlag"
    PrecisionRule="true"
    EntityAttrName="ActiveFlag"
    EntityUsage="LocationMstEO"
    AliasName="Active_Flag"
    DefaultValue="Y">
    <Properties>
      <SchemaBasedProperties>
        <CONTROLTYPE
          Value="check_box"/>
      </SchemaBasedProperties>
    </Properties>
  </ViewAttribute>
  <ViewAttribute
    Name="AddlCharge"
    PrecisionRule="true"
    EntityAttrName="AddlCharge"
    EntityUsage="LocationMstEO"
    AliasName="Addl_Charge"/>
  <ViewAttribute
    Name="BayCount"
    PrecisionRule="true"
    EntityAttrName="BayCount"
    EntityUsage="LocationMstEO"
    AliasName="Bay_Count"/>
  <ViewAttribute
    Name="COUNTRYCODE"
    LOVName="LOV_COUNTRYCODE"
    PrecisionRule="true"
    EntityAttrName="COUNTRYCODE"
    EntityUsage="LocationMstEO"
    AliasName="COUNTRY_CODE">
    <Properties>
      <SchemaBasedProperties>
        <CONTROLTYPE
          Value="choice"/>
      </SchemaBasedProperties>
    </Properties>
  </ViewAttribute>
  <ViewAttribute
    Name="Clampingcharges"
    PrecisionRule="true"
    EntityAttrName="Clampingcharges"
    EntityUsage="LocationMstEO"
    AliasName="Clamping_charges"/>
  <ViewAttribute
    Name="CommunityCode"
    LOVName="LOV_CommunityCode"
    IsNotNull="true"
    PrecisionRule="true"
    EntityAttrName="CommunityCode"
    EntityUsage="LocationMstEO"
    AliasName="Community_Code">
    <Properties>
      <SchemaBasedProperties>
        <CONTROLTYPE
          Value="choice"/>
      </SchemaBasedProperties>
    </Properties>
  </ViewAttribute>
  <ViewAttribute
    Name="ContactDetails"
    PrecisionRule="true"
    EntityAttrName="ContactDetails"
    EntityUsage="LocationMstEO"
    AliasName="Contact_Details"/>
  <ViewAttribute
    Name="CreatedBy"
    IsNotNull="true"
    PrecisionRule="true"
    EntityAttrName="CreatedBy"
    EntityUsage="LocationMstEO"
    AliasName="Created_By"/>
  <ViewAttribute
    Name="CreatedDate"
    IsNotNull="true"
    PrecisionRule="true"
    EntityAttrName="CreatedDate"
    EntityUsage="LocationMstEO"
    AliasName="Created_Date"/>
  <ViewAttribute
    Name="Freedays"
    PrecisionRule="true"
    EntityAttrName="Freedays"
    EntityUsage="LocationMstEO"
    AliasName="Free_days"/>
  <ViewAttribute
    Name="Geolatdeg"
    PrecisionRule="true"
    EntityAttrName="Geolatdeg"
    EntityUsage="LocationMstEO"
    AliasName="Geo_lat_deg"/>
  <ViewAttribute
    Name="Geolondeg"
    PrecisionRule="true"
    EntityAttrName="Geolondeg"
    EntityUsage="LocationMstEO"
    AliasName="Geo_lon_deg"/>
  <ViewAttribute
    Name="GoLiveDt"
    PrecisionRule="true"
    EntityAttrName="GoLiveDt"
    EntityUsage="LocationMstEO"
    AliasName="GoLive_Dt"/>
  <ViewAttribute
    Name="LOCTYPE"
    LOVName="LOV_LOCTYPE"
    PrecisionRule="true"
    EntityAttrName="LOCTYPE"
    EntityUsage="LocationMstEO"
    AliasName="LOC_TYPE">
    <Properties>
      <SchemaBasedProperties>
        <CONTROLTYPE
          Value="choice"/>
      </SchemaBasedProperties>
    </Properties>
  </ViewAttribute>
  <ViewAttribute
    Name="LocAdd1"
    PrecisionRule="true"
    EntityAttrName="LocAdd1"
    EntityUsage="LocationMstEO"
    AliasName="Loc_Add1"/>
  <ViewAttribute
    Name="LocAdd2"
    PrecisionRule="true"
    EntityAttrName="LocAdd2"
    EntityUsage="LocationMstEO"
    AliasName="Loc_Add2"/>
  <ViewAttribute
    Name="LocDesc"
    PrecisionRule="true"
    EntityAttrName="LocDesc"
    EntityUsage="LocationMstEO"
    AliasName="Loc_Desc"/>
  <ViewAttribute
    Name="LocationID"
    IsUpdateable="false"
    PrecisionRule="true"
    EntityAttrName="LocationID"
    EntityUsage="LocationMstEO"
    AliasName="Location_ID"/>
  <ViewAttribute
    Name="OpeningDt"
    PrecisionRule="true"
    EntityAttrName="OpeningDt"
    EntityUsage="LocationMstEO"
    AliasName="Opening_Dt"/>
  <ViewAttribute
    Name="OprHrFrom"
    PrecisionRule="true"
    EntityAttrName="OprHrFrom"
    EntityUsage="LocationMstEO"
    AliasName="Opr_Hr_From">
    <Properties>
      <SchemaBasedProperties>
        <DISPLAYWIDTH
          Value="10"/>
      </SchemaBasedProperties>
    </Properties>
  </ViewAttribute>
  <ViewAttribute
    Name="OprHrTo"
    PrecisionRule="true"
    EntityAttrName="OprHrTo"
    EntityUsage="LocationMstEO"
    AliasName="Opr_Hr_To">
    <Properties>
      <SchemaBasedProperties>
        <DISPLAYWIDTH
          Value="10"/>
      </SchemaBasedProperties>
    </Properties>
  </ViewAttribute>
  <ViewAttribute
    Name="POBox"
    PrecisionRule="true"
    EntityAttrName="POBox"
    EntityUsage="LocationMstEO"
    AliasName="PO_Box"/>
  <ViewAttribute
    Name="RemovalCharge"
    PrecisionRule="true"
    EntityAttrName="RemovalCharge"
    EntityUsage="LocationMstEO"
    AliasName="Removal_Charge"/>
  <ViewAttribute
    Name="UpdatedBy"
    PrecisionRule="true"
    EntityAttrName="UpdatedBy"
    EntityUsage="LocationMstEO"
    AliasName="Updated_By"/>
  <ViewAttribute
    Name="UpdatedDate"
    PrecisionRule="true"
    EntityAttrName="UpdatedDate"
    EntityUsage="LocationMstEO"
    AliasName="Updated_Date"/>
  <ViewAttribute
    Name="issCommPrmitflag"
    PrecisionRule="true"
    EntityAttrName="issCommPrmitflag"
    EntityUsage="LocationMstEO"
    AliasName="iss_Comm_Prmit_flag"/>
  <ViewAttribute
    Name="issGovtPermitflag"
    PrecisionRule="true"
    EntityAttrName="issGovtPermitflag"
    EntityUsage="LocationMstEO"
    AliasName="iss_Govt_Permit_flag"/>
  <ViewAttribute
    Name="Remarks"
    PrecisionRule="true"
    EntityAttrName="Remarks"
    EntityUsage="LocationMstEO"
    AliasName="Remarks">
    <Properties>
      <SchemaBasedProperties>
        <LABEL
          ResId="com.imum.cpms.model.masters.vo.LocationMstVO.Remarks_LABEL"/>
      </SchemaBasedProperties>
    </Properties>
  </ViewAttribute>
  <ViewAttribute
    Name="AllowCommercialPermitsflag"
    PrecisionRule="true"
    EntityAttrName="AllowCommercialPermitsflag"
    EntityUsage="LocationMstEO"
    AliasName="Allow_Commercial_Permits_flag"/>
  <ViewAttribute
    Name="Storagecharge"
    PrecisionRule="true"
    EntityAttrName="Storagecharge"
    EntityUsage="LocationMstEO"
    AliasName="Storage_charge"/>
  <ViewAttribute
    Name="CountryName"
    IsUpdateable="false"
    IsPersistent="false"
    PrecisionRule="true"
    Precision="200"
    Type="java.lang.String"
    ColumnType="varchar"
    AliasName="Country_Name"
    Expression="Country_Name"
    SQLType="VARCHAR">
    <DesignTime>
      <Attr Name="_DisplaySize" Value="200"/>
    </DesignTime>
  </ViewAttribute>
  <ViewAttribute
    Name="CommunityName"
    IsUpdateable="false"
    IsPersistent="false"
    PrecisionRule="true"
    Precision="200"
    Type="java.lang.String"
    ColumnType="varchar"
    AliasName="Community_Name"
    Expression="Community_Name"
    SQLType="VARCHAR">
    <DesignTime>
      <Attr Name="_DisplaySize" Value="200"/>
    </DesignTime>
  </ViewAttribute>
  <ViewAttribute
    Name="LocationTypeName"
    IsUpdateable="false"
    IsPersistent="false"
    PrecisionRule="true"
    Precision="30"
    Type="java.lang.String"
    ColumnType="varchar"
    AliasName="LocationType_Name"
    Expression="LocationType_Name"
    SQLType="VARCHAR">
    <DesignTime>
      <Attr Name="_DisplaySize" Value="30"/>
    </DesignTime>
  </ViewAttribute>
  <ViewAttribute
    Name="Language"
    IsSelected="false"
    IsPersistent="false"
    PrecisionRule="true"
    Type="java.lang.String"
    ColumnType="VARCHAR2"
    AliasName="VIEW_ATTR"
    SQLType="VARCHAR"
    LOVName="LOV_Language">
    <TransientExpression><![CDATA[adf.context.locale.language=='en'?'AR':'EN']]></TransientExpression>
    <Properties>
      <SchemaBasedProperties>
        <CONTROLTYPE
          Value="choice"/>
      </SchemaBasedProperties>
    </Properties>
  </ViewAttribute>
  <ViewAttribute
    Name="LocationNameLng"
    IsSelected="false"
    IsPersistent="false"
    PrecisionRule="true"
    Type="java.lang.String"
    ColumnType="VARCHAR2"
    AliasName="VIEW_ATTR"
    SQLType="VARCHAR"/>
  <ResourceBundle>
    <PropertiesBundle
      PropertiesFile="com.imum.cpms.model.ModelBundle"/>
  </ResourceBundle>
</ViewObject>
