<?xml version="1.0" encoding="windows-1252" ?>
<adfc-config xmlns="http://xmlns.oracle.com/adf/controller" version="1.2">
  <managed-bean id="__3">
    <managed-bean-name id="__4">backing_home</managed-bean-name>
    <managed-bean-class id="__1">com.imum.cpms.view.backing.Home</managed-bean-class>
    <managed-bean-scope id="__2">backingBean</managed-bean-scope>
  </managed-bean>
  <managed-bean id="__6">
    <managed-bean-name id="__8">TemplateBean</managed-bean-name>
    <managed-bean-class id="__7">com.imum.cpms.view.TemplateBean</managed-bean-class>
    <managed-bean-scope id="__5">session</managed-bean-scope>
  </managed-bean>
  <managed-bean id="__9">
    <managed-bean-name id="__11">backing_LoginPage</managed-bean-name>
    <managed-bean-class id="__10">com.imum.cpms.login.backing_LoginPage</managed-bean-class>
    <managed-bean-scope id="__12">backingBean</managed-bean-scope>
  </managed-bean>
  <managed-bean id="__17">
    <managed-bean-name id="__19">InventoryUploadMBean</managed-bean-name>
    <managed-bean-class id="__18">com.imum.cpms.transactions.inventory.inventoryUploadMBean</managed-bean-class>
    <managed-bean-scope id="__20">backingBean</managed-bean-scope>
  </managed-bean>
  <managed-bean id="__15">
    <managed-bean-name id="__13">poundBayAllocTBean</managed-bean-name>
    <managed-bean-class id="__16">com.imum.cpms.transactions.PoundBayAllocationBean</managed-bean-class>
    <managed-bean-scope id="__14">pageFlow</managed-bean-scope>
  </managed-bean>
  <managed-bean id="__24">
    <managed-bean-name id="__22">pvtOnHoldReleaseBean</managed-bean-name>
    <managed-bean-class id="__21">com.imum.cpms.transactions.PVTOnHoldReleaseBean</managed-bean-class>
    <managed-bean-scope id="__23">pageFlow</managed-bean-scope>
  </managed-bean>
  <managed-bean id="__29">
    <managed-bean-name id="__30">vehWhitelistMstBean</managed-bean-name>
    <managed-bean-class id="__32">com.imum.cpms.VehicleWhitelistMstBean</managed-bean-class>
    <managed-bean-scope id="__31">pageFlow</managed-bean-scope>
  </managed-bean>
  <managed-bean id="__35">
    <managed-bean-name id="__33">localeBean</managed-bean-name>
    <managed-bean-class id="__36">com.imum.cpms.login.LocaleBean</managed-bean-class>
    <managed-bean-scope id="__34">session</managed-bean-scope>
  </managed-bean>
  <managed-bean id="__40">
    <managed-bean-name id="__37">PVTDetailsMBean</managed-bean-name>
    <managed-bean-class id="__39">com.imum.cpms.PVTDetailsMBean</managed-bean-class>
    <managed-bean-scope id="__38">pageFlow</managed-bean-scope>
  </managed-bean>
  <managed-bean id="__37">
    <managed-bean-name id="__40">PIWorkAssign</managed-bean-name>
    <managed-bean-class id="__39">com.imum.cpms.staffdeploy.PIWorkAssign</managed-bean-class>
    <managed-bean-scope id="__38">request</managed-bean-scope>
  </managed-bean>
  <managed-bean id="__26">
    <managed-bean-name id="__28">accountMstBean</managed-bean-name>
    <managed-bean-class id="__27">com.imum.cpms.AccountMstBean</managed-bean-class>
    <managed-bean-scope id="__25">pageFlow</managed-bean-scope>
  </managed-bean>
  <managed-bean id="__42">
    <managed-bean-name id="__44">PVTAmountAdjMBean</managed-bean-name>
    <managed-bean-class id="__41">com.imum.cpms.transactions.PVTAmtAdjMBean</managed-bean-class>
    <managed-bean-scope id="__43">pageFlow</managed-bean-scope>
  </managed-bean>
  <managed-bean id="__47">
    <managed-bean-name id="__46">ADPSearchReportMBean</managed-bean-name>
    <managed-bean-class id="__45">com.imum.cpms.view.ADPSearchReportMBean</managed-bean-class>
    <managed-bean-scope id="__48">pageFlow</managed-bean-scope>
  </managed-bean>
  <managed-bean id="__45">
    <managed-bean-name id="__46">CreateTable</managed-bean-name>
    <managed-bean-class id="__47">com.imum.cpms.staffdeploy.CreateTable</managed-bean-class>
    <managed-bean-scope id="__48">request</managed-bean-scope>
  </managed-bean>
  <managed-bean id="__49">
    <managed-bean-name id="__50">vehBlacklistMstBean</managed-bean-name>
    <managed-bean-class id="__51">com.imum.cpms.VehicleBlacklistMstBean</managed-bean-class>
    <managed-bean-scope id="__52">pageFlow</managed-bean-scope>
  </managed-bean>
  <managed-bean id="__54">
    <managed-bean-name id="__53">PVTPaymentsLOGMBean</managed-bean-name>
    <managed-bean-class id="__55">com.imum.cpms.view.PVTPaymentsLOGMBean</managed-bean-class>
    <managed-bean-scope id="__56">pageFlow</managed-bean-scope>
  </managed-bean>
  <managed-bean id="__57">
    <managed-bean-name id="__58">AuditCardsNewMBean</managed-bean-name>
    <managed-bean-class id="__60">com.imum.cpms.view.AuditCardsNewMBean</managed-bean-class>
    <managed-bean-scope id="__59">pageFlow</managed-bean-scope>
  </managed-bean>
  <managed-bean id="__62">
    <managed-bean-name id="__64">BeatMstBean</managed-bean-name>
    <managed-bean-class id="__61">com.imum.cpms.view.BeatMstBean</managed-bean-class>
    <managed-bean-scope id="__63">pageFlow</managed-bean-scope>
  </managed-bean>
  <managed-bean id="__66">
    <managed-bean-name id="__68">PaymentsAmmMBean</managed-bean-name>
    <managed-bean-class id="__67">com.imum.cpms.view.PaymentsAmmMBean</managed-bean-class>
    <managed-bean-scope id="__65">pageFlow</managed-bean-scope>
  </managed-bean>
</adfc-config>
